templateflow/__init__.py
templateflow/_version.py
templateflow/api.py
templateflow/cli.py
templateflow/client.py
templateflow/conf/__init__.py
templateflow/conf/_s3.py
templateflow/conf/bids.py
templateflow/conf/cache.py
templateflow/conf/config.json
templateflow/conf/env.py
templateflow/conf/templateflow-skel.md5
templateflow/conf/templateflow-skel.zip
templateflow/tests/__init__.py
templateflow/tests/test_api.py
templateflow/tests/test_cli.py
templateflow/tests/test_conf.py
templateflow/tests/test_multiproc.py
templateflow/tests/test_s3.py
templateflow/tests/test_version.py
templateflow/tests/data/__init__.py
templateflow/tests/data/error_response.xml
templateflow-25.1.1.dist-info/METADATA
templateflow-25.1.1.dist-info/WHEEL
templateflow-25.1.1.dist-info/entry_points.txt
templateflow-25.1.1.dist-info/licenses/LICENSE
templateflow-25.1.1.dist-info/RECORD
