Metadata-Version: 2.4
Name: templateflow
Version: 25.1.1
Summary: TemplateFlow Python Client - TemplateFlow is the Zone of neuroimaging templates.
Project-URL: Archive, https://github.com/templateflow/templateflow
Project-URL: Bug Tracker, https://github.com/templateflow/python-client/issues
Project-URL: Home, https://www.templateflow.org
Project-URL: Documentation, https://www.templateflow.org/python-client/
Project-URL: Source Code, https://github.com/templateflow/python-client
Author-email: The NiPreps Developers <nipreps@gmail.com>
License:                                  Apache License
License-File: LICENSE
Classifier: Development Status :: 3 - Alpha
Classifier: Intended Audience :: Science/Research
Classifier: License :: OSI Approved :: Apache Software License
Classifier: Programming Language :: Python :: 3.9
Classifier: Programming Language :: Python :: 3.10
Classifier: Programming Language :: Python :: 3.11
Classifier: Programming Language :: Python :: 3.12
Classifier: Programming Language :: Python :: 3.13
Classifier: Topic :: Scientific/Engineering :: Image Recognition
Requires-Python: >=3.9
Requires-Dist: acres>=0.5.0
Requires-Dist: platformdirs>=4.0
Requires-Dist: pybids>=0.15.2
Requires-Dist: requests
Requires-Dist: tqdm
Provides-Extra: all
Requires-Dist: coverage~=5.0.0; extra == 'all'
Requires-Dist: datalad>=1.0.0; extra == 'all'
Requires-Dist: nbsphinx; extra == 'all'
Requires-Dist: packaging; extra == 'all'
Requires-Dist: pydot>=1.2.3; extra == 'all'
Requires-Dist: pydotplus; extra == 'all'
Requires-Dist: pytest; extra == 'all'
Requires-Dist: pytest-cov; extra == 'all'
Requires-Dist: pytest-env; extra == 'all'
Requires-Dist: pytest-xdist; extra == 'all'
Requires-Dist: sphinx-click; extra == 'all'
Requires-Dist: sphinx-multiversion; extra == 'all'
Requires-Dist: sphinx-rtd-theme>=0.4.3; extra == 'all'
Requires-Dist: sphinxcontrib-apidoc; extra == 'all'
Requires-Dist: sphinx~=4.0; extra == 'all'
Requires-Dist: toml; extra == 'all'
Provides-Extra: datalad
Requires-Dist: datalad>=1.0.0; extra == 'datalad'
Provides-Extra: doc
Requires-Dist: nbsphinx; extra == 'doc'
Requires-Dist: packaging; extra == 'doc'
Requires-Dist: pydot>=1.2.3; extra == 'doc'
Requires-Dist: pydotplus; extra == 'doc'
Requires-Dist: sphinx-click; extra == 'doc'
Requires-Dist: sphinx-multiversion; extra == 'doc'
Requires-Dist: sphinx-rtd-theme>=0.4.3; extra == 'doc'
Requires-Dist: sphinxcontrib-apidoc; extra == 'doc'
Requires-Dist: sphinx~=4.0; extra == 'doc'
Provides-Extra: docs
Requires-Dist: nbsphinx; extra == 'docs'
Requires-Dist: packaging; extra == 'docs'
Requires-Dist: pydot>=1.2.3; extra == 'docs'
Requires-Dist: pydotplus; extra == 'docs'
Requires-Dist: sphinx-click; extra == 'docs'
Requires-Dist: sphinx-multiversion; extra == 'docs'
Requires-Dist: sphinx-rtd-theme>=0.4.3; extra == 'docs'
Requires-Dist: sphinxcontrib-apidoc; extra == 'docs'
Requires-Dist: sphinx~=4.0; extra == 'docs'
Provides-Extra: test
Requires-Dist: coverage~=5.0.0; extra == 'test'
Requires-Dist: pytest; extra == 'test'
Requires-Dist: pytest-cov; extra == 'test'
Requires-Dist: pytest-env; extra == 'test'
Requires-Dist: pytest-xdist; extra == 'test'
Requires-Dist: toml; extra == 'test'
Provides-Extra: tests
Requires-Dist: coverage~=5.0.0; extra == 'tests'
Requires-Dist: pytest; extra == 'tests'
Requires-Dist: pytest-cov; extra == 'tests'
Requires-Dist: pytest-env; extra == 'tests'
Requires-Dist: pytest-xdist; extra == 'tests'
Requires-Dist: toml; extra == 'tests'
